Metadata-Version: 2.4
Name: iflow-mcp_semanticscholar-mcp-server
Version: 0.1.0
Summary: A Model Context Protocol server for Semantic Scholar API integration
Author-email: JackKuo666 <example@example.com>
Requires-Python: >=3.10
Requires-Dist: mcp>=1.0.0
Requires-Dist: semanticscholar>=0.8.0
Requires-Dist: requests>=2.25.1
Requires-Dist: beautifulsoup4>=4.9.3
